{"type": "FeatureCollection", "features": [{"type": "Feature", "properties": {"name": "Beitou"}, "geometry": {"type": "Point", "coordinates": [121.505, 25.13]}}, {"type": "Feature", "properties": {"name": "Taipei Main"}, "geometry": {"type": "Point", "coordinates": [121.517, 25.05]}}, {"type": "Feature", "properties": {"name": "Taipei 101"}, "geometry": {"type": "Point", "coordinates": [121.565, 25.033]}}, {"type": "Feature", "properties": {"name": "Ximen"}, "geometry": {"type": "Point", "coordinates": [121.5, 25.04]}}, {"type": "Feature", "properties": {"name": "Nangang"}, "geometry": {"type": "Point", "coordinates": [121.6, 25.05]}}]}
